Workbook

Sheet 01_Assumptions
A1: 1. Operational assumptions
A3: Parameter | B3: Value | C3: Unit | D3: Source | E3: Notes
A4: Project type | B4: Utility-scale solar PV | C4: N/A
A5: Project location | B5: France | C5: N/A
A6: Installed capacity | B6: 100 | C6: MWp
A7: Project lifetime | B7: 25 | C7: year
A8: Construction period | B8: 1 | C8: year
A9: Operation period | B9: 25 | C9: year
A10: Capacity factor | B10: 0.141 | C10: % | D10: https://analysesetdonnees.rte-france.com/en/generation/solar | E10: Average capacity factor for solar generation in France
A11: CAPEX | B11: 85 | C11: M€ | D11: https://www.solardataatlas.com/en/data-solar-capex-europe | E11: France CAPEX for utility-scale solar PV for the year 2026 : price range: 750 - 950 (€/kWp) - HT midpoint used as base case = 850 k€/kWp
A12: OPEX | B12: 1.1 | C12: M€/year | D12: https://www.solardataatlas.com/en/data-solar-opex-europe | E12: France OPEX for utility-scale solar PV for the year 2026 : price range: 9 - 13 (€/Kwp/year) - HT midpoint used as base case = 11 €/kWp/year
A13: Degradation | B13: 0.005 | C13: %/year | D13: Solar Panel Degradation Rates - Greensolver
A14: PPA electricity price | B14: 59 | C14: €/MWh | D14: https://www.solardataatlas.com/en/data-solar-ppa-prices-europe | E14: France PPA price range for the year 2026 price range: €50–68/MWh; midpoint used as base case = 59 €/MWh
A15: Inflation | B15: 0.02 | C15: % | D15: https://www.banque-france.fr/fr/publications-et-statistiques/publications/quest-ce-que-la-politique-monetaire | E15: Assumption: 2% long-term inflation consistent with the ECB's medium-term inflation target
A18: 2. Financial assumptions
A20: Parameter | B20: Value | C20: Unit | D20: Source | E20: Notes
A21: Corporate tax rate | B21: 0.25 | C21: % | D21: Impôt sur les sociétés |impots.gouv.fr | E21: N/A
A22: Debt share | B22: 0.75 | C22: % | D22: N/A | E22: Assumption for utility-scale solar PV projects
A23: Equity share | B23: 0.25 | C23: % | D23: N/A | E23: Assumption for utility-scale solar PV projects
A24: Debt tenor | B24: 15 | C24: year | D24: N/A | E24: Assumption for utility-scale solar PV projects
A25: Cost of Debt (Interest rate) | B25: 0.0225 | C25: % | D25: Solar WACC Europe 2026 | Solar Data Atlas | E25: Cost of Debt for solar PV utility-scale projects in France; range: 1.5 – 3.0%
A26: Cost of Equity | B26: 0.08 | C26: % | D26: Solar WACC Europe 2026 | Solar Data Atlas | E26: Cost of Equity for solar PV utility-scale projects in France; range: 6 – 10%
A27: WACC | B27: =B22*B25*(1-B21)+B23*B26 -> 0.03265625 | C27: % | D27: Solar WACC Europe 2026 | Solar Data Atlas | E27: Calculated
A28: Discount rate | B28: =B27 -> 0.03265625 | C28: % | D28: N/A | E28: Assumed equal to WACC for project DCF
A29: Risk premium | B29: 0.02 | C29: % | D29: N/A | E29: Assumption for additional project risk
A30: Hurdle rate | B30: =B27+B29 -> 0.05265625 | C30: % | D30: N/A | E30: WACC + project risk premium
A37: Definitions:
A38: CAPEX: Capital Expenditure is the upfront investment required to build and equip the solar project.
A39: OPEX: Operating Expenditure represents the recurring costs required to operate and maintain the solar project.

Sheet 02_Operations
A2: Paremeter | B2: Unit | C2: Year 0 | D2: Year 1 | E2: Year 2 | F2: Year 3 | G2: Year 4 | H2: Year 5 | I2: Year 6 | J2: Year 7 | K2: Year 8 | L2: Year 9 | M2: Year 10 | N2: Year 11 | O2: Year 12 | P2: Year 13 | Q2: Year 14 | R2: Year 15 | S2: Year 16 | T2: Year 17 | U2: Year 18 | V2: Year 19 | W2: Year 20 | X2: Year 21 | Y2: Year 22 | Z2: Year 23 | AA2: Year 24 | AB2: Year 25
A3: Installed Capacity | B3: MWp | C3: 100 | D3: 100 | E3: 100 | F3: 100 | G3: 100 | H3: 100 | I3: 100 | J3: 100 | K3: 100 | L3: 100 | M3: 100 | N3: 100 | O3: 100 | P3: 100 | Q3: 100 | R3: 100 | S3: 100 | T3: 100 | U3: 100 | V3: 100 | W3: 100 | X3: 100 | Y3: 100 | Z3: 100 | AA3: 100 | AB3: 100
A4: Hours per year | B4: h | C4: 0 | D4: 8760 | E4: 8760 | F4: 8760 | G4: 8760 | H4: 8760 | I4: 8760 | J4: 8760 | K4: 8760 | L4: 8760 | M4: 8760 | N4: 8760 | O4: 8760 | P4: 8760 | Q4: 8760 | R4: 8760 | S4: 8760 | T4: 8760 | U4: 8760 | V4: 8760 | W4: 8760 | X4: 8760 | Y4: 8760 | Z4: 8760 | AA4: 8760 | AB4: 8760
A5: Capacity Factor | B5: % | C5: 0.141 | D5: 0.141 | E5: 0.141 | F5: 0.141 | G5: 0.141 | H5: 0.141 | I5: 0.141 | J5: 0.141 | K5: 0.141 | L5: 0.141 | M5: 0.141 | N5: 0.141 | O5: 0.141 | P5: 0.141 | Q5: 0.141 | R5: 0.141 | S5: 0.141 | T5: 0.141 | U5: 0.141 | V5: 0.141 | W5: 0.141 | X5: 0.141 | Y5: 0.141 | Z5: 0.141 | AA5: 0.141 | AB5: 0.141
A6: Gross Annual Production | B6: MWh | C6: =C3*C4*C5 -> 0 | D6: =D3*D4*D5*(1-C7) -> 123516 | E6: =Table3[[#This Row],[Year 1]]*(1-D7) -> 122898.42 | F6: =Table3[[#This Row],[Year 2]]*(1-E7) -> 122283.93 | G6: =Table3[[#This Row],[Year 3]]*(1-F7) -> 121672.51 | H6: =Table3[[#This Row],[Year 4]]*(1-G7) -> 121064.15 | I6: =Table3[[#This Row],[Year 5]]*(1-H7) -> 120458.82 | J6: =Table3[[#This Row],[Year 6]]*(1-I7) -> 119856.53 | K6: =Table3[[#This Row],[Year 7]]*(1-J7) -> 119257.25 | L6: =Table3[[#This Row],[Year 8]]*(1-K7) -> 118660.96 | M6: =Table3[[#This Row],[Year 9]]*(1-L7) -> 118067.66 | N6: =Table3[[#This Row],[Year 10]]*(1-M7) -> 117477.32 | O6: =Table3[[#This Row],[Year 11]]*(1-N7) -> 116889.93 | P6: =Table3[[#This Row],[Year 12]]*(1-O7) -> 116305.48 | Q6: =Table3[[#This Row],[Year 13]]*(1-P7) -> 115723.96 | R6: =Table3[[#This Row],[Year 14]]*(1-Q7) -> 115145.34 | S6: =Table3[[#This Row],[Year 15]]*(1-R7) -> 114569.61 | T6: =Table3[[#This Row],[Year 16]]*(1-S7) -> 113996.76 | U6: =Table3[[#This Row],[Year 17]]*(1-T7) -> 113426.78 | V6: =Table3[[#This Row],[Year 18]]*(1-U7) -> 112859.64 | W6: =Table3[[#This Row],[Year 19]]*(1-V7) -> 112295.34 | X6: =Table3[[#This Row],[Year 20]]*(1-W7) -> 111733.87 | Y6: =Table3[[#This Row],[Year 21]]*(1-X7) -> 111175.2 | Z6: =Table3[[#This Row],[Year 22]]*(1-Y7) -> 110619.32 | AA6: =Table3[[#This Row],[Year 23]]*(1-Z7) -> 110066.23 | AB6: =Table3[[#This Row],[Year 24]]*(1-AA7) -> 109515.9
A7: Degradation | B7: % | C7: 0 | D7: 0.005 | E7: 0.005 | F7: 0.005 | G7: 0.005 | H7: 0.005 | I7: 0.005 | J7: 0.005 | K7: 0.005 | L7: 0.005 | M7: 0.005 | N7: 0.005 | O7: 0.005 | P7: 0.005 | Q7: 0.005 | R7: 0.005 | S7: 0.005 | T7: 0.005 | U7: 0.005 | V7: 0.005 | W7: 0.005 | X7: 0.005 | Y7: 0.005 | Z7: 0.005 | AA7: 0.005 | AB7: 0.005
A8: System losses | B8: % | C8: 0 | D8: 0.14 | E8: 0.14 | F8: 0.14 | G8: 0.14 | H8: 0.14 | I8: 0.14 | J8: 0.14 | K8: 0.14 | L8: 0.14 | M8: 0.14 | N8: 0.14 | O8: 0.14 | P8: 0.14 | Q8: 0.14 | R8: 0.14 | S8: 0.14 | T8: 0.14 | U8: 0.14 | V8: 0.14 | W8: 0.14 | X8: 0.14 | Y8: 0.14 | Z8: 0.14 | AA8: 0.14 | AB8: 0.14
A9: Net Electricity Production | B9: MWh | C9: 0 | D9: =D6*(1-D8) -> 106223.76 | E9: =E6*(1-E8) -> 105692.64 | F9: =F6*(1-F8) -> 105164.18 | G9: =G6*(1-G8) -> 104638.36 | H9: =H6*(1-H8) -> 104115.17 | I9: =I6*(1-I8) -> 103594.59 | J9: =J6*(1-J8) -> 103076.62 | K9: =K6*(1-K8) -> 102561.23 | ... AB9: =AB6*(1-AB8) -> 94183.67
A13: Definitions:
A14: Degradation: the gradual loss of a solar panel's ability to produce electricity over time.
A15: System losses: electricity lost during the operation and transmission of the PV system (e.g. wiring, inverter, soiling, shading, mismatch, etc.).

Sheet 03_Revenues
A2: Paremeter | B2: Unit | C2: Year 0 | D2: Year 1 | E2: Year 2 | F2: Year 3 | G2: Year 4 | H2: Year 5 | I2: Year 6 | J2: Year 7 | K2: Year 8 | L2: Year 9 | M2: Year 10 | N2: Year 11 | O2: Year 12 | P2: Year 13 | Q2: Year 14 | R2: Year 15 | S2: Year 16 | T2: Year 17 | U2: Year 18 | V2: Year 19 | W2: Year 20 | X2: Year 21 | Y2: Year 22 | Z2: Year 23 | AA2: Year 24 | AB2: Year 25
A3: Net Electricity Production | B3: MWh | C3: ='02_Operations'!C9 -> 0 | D3: ='02_Operations'!D9 -> 106223.76 | E3: ='02_Operations'!E9 -> 105692.64 | F3: ='02_Operations'!F9 -> 105164.18 | G3: ='02_Operations'!G9 -> 104638.36 | H3: ='02_Operations'!H9 -> 104115.17 | I3: ='02_Operations'!I9 -> 103594.59 | J3: ='02_Operations'!J9 -> 103076.62 | ... AB3: ='02_Operations'!AB9 -> 94183.67
A4: PPA electricity price | B4: €/MWh | C4: 59 | D4: =Table35[[#This Row],[Year 0]]*(1+'01_Assumptions'!$B$15) -> 60.18 | E4: =Table35[[#This Row],[Year 1]]*(1+'01_Assumptions'!$B$15) -> 61.3836 | F4: =Table35[[#This Row],[Year 2]]*(1+'01_Assumptions'!$B$15) -> 62.611272 | G4: =Table35[[#This Row],[Year 3]]*(1+'01_Assumptions'!$B$15) -> 63.863497 | H4: =Table35[[#This Row],[Year 4]]*(1+'01_Assumptions'!$B$15) -> 65.140767 | I4: =Table35[[#This Row],[Year 5]]*(1+'01_Assumptions'!$B$15) -> 66.443583 | J4: =Table35[[#This Row],[Year 6]]*(1+'01_Assumptions'!$B$15) -> 67.772454 | K4: =Table35[[#This Row],[Year 7]]*(1+'01_Assumptions'!$B$15) -> 69.127903 | L4: =Table35[[#This Row],[Year 8]]*(1+'01_Assumptions'!$B$15) -> 70.510462 | M4: =Table35[[#This Row],[Year 9]]*(1+'01_Assumptions'!$B$15) -> 71.920671 | N4: =Table35[[#This Row],[Year 10]]*(1+'01_Assumptions'!$B$15) -> 73.359084 | O4: =Table35[[#This Row],[Year 11]]*(1+'01_Assumptions'!$B$15) -> 74.826266 | P4: =Table35[[#This Row],[Year 12]]*(1+'01_Assumptions'!$B$15) -> 76.322791 | Q4: =Table35[[#This Row],[Year 13]]*(1+'01_Assumptions'!$B$15) -> 77.849247 | R4: =Table35[[#This Row],[Year 14]]*(1+'01_Assumptions'!$B$15) -> 79.406232 | S4: =Table35[[#This Row],[Year 15]]*(1+'01_Assumptions'!$B$15) -> 80.994357 | T4: =Table35[[#This Row],[Year 16]]*(1+'01_Assumptions'!$B$15) -> 82.614244 | U4: =Table35[[#This Row],[Year 17]]*(1+'01_Assumptions'!$B$15) -> 84.266529 | V4: =Table35[[#This Row],[Year 18]]*(1+'01_Assumptions'!$B$15) -> 85.951859 | W4: =Table35[[#This Row],[Year 19]]*(1+'01_Assumptions'!$B$15) -> 87.670896 | X4: =Table35[[#This Row],[Year 20]]*(1+'01_Assumptions'!$B$15) -> 89.424314 | Y4: =Table35[[#This Row],[Year 21]]*(1+'01_Assumptions'!$B$15) -> 91.212801 | Z4: =Table35[[#This Row],[Year 22]]*(1+'01_Assumptions'!$B$15) -> 93.037057 | AA4: =Table35[[#This Row],[Year 23]]*(1+'01_Assumptions'!$B$15) -> 94.897798 | AB4: =Table35[[#This Row],[Year 24]]*(1+'01_Assumptions'!$B$15) -> 96.795754
A5: Annual Revenue | B5: € | C5: =C4*C3 -> 0 | D5: =D4*D3 -> 6392545.9 | E5: =E4*E3 -> 6487794.8 | F5: =F4*F3 -> 6584463 | G5: =G4*G3 -> 6682571.5 | H5: =H4*H3 -> 6782141.8 | I5: =I4*I3 -> 6883195.7 | J5: =J4*J3 -> 6985755.3 | ... AB5: =AB4*AB3 -> 9116579.3

Sheet 04_Costs
A2: Parameter | B2: Unit | C2: Year 0 | D2: Year 1 | E2: Year 2 | F2: Year 3 | G2: Year 4 | H2: Year 5 | I2: Year 6 | J2: Year 7 | K2: Year 8 | L2: Year 9 | M2: Year 10 | N2: Year 11 | O2: Year 12 | P2: Year 13 | Q2: Year 14 | R2: Year 15 | S2: Year 16 | T2: Year 17 | U2: Year 18 | V2: Year 19 | W2: Year 20 | X2: Year 21 | Y2: Year 22 | Z2: Year 23 | AA2: Year 24 | AB2: Year 25
A3: Annual Revenue | B3: € | C3: ='03_Revenues'!C5 -> 0 | D3: ='03_Revenues'!D5 -> 6392545.9 | E3: ='03_Revenues'!E5 -> 6487794.8 | F3: ='03_Revenues'!F5 -> 6584463 | G3: ='03_Revenues'!G5 -> 6682571.5 | H3: ='03_Revenues'!H5 -> 6782141.8 | I3: ='03_Revenues'!I5 -> 6883195.7 | J3: ='03_Revenues'!J5 -> 6985755.3 | ... AB3: ='03_Revenues'!AB5 -> 9116579.3
A4: OPEX | B4: € | C4: 0 | D4: ='01_Assumptions'!$B$12*(10^6)*(1+'01_Assumptions'!B15) -> 1122000 | E4: =Table5[[#This Row],[Year 1]]*(1+'01_Assumptions'!$B$15) -> 1144440 | F4: =Table5[[#This Row],[Year 2]]*(1+'01_Assumptions'!$B$15) -> 1167328.8 | G4: =Table5[[#This Row],[Year 3]]*(1+'01_Assumptions'!$B$15) -> 1190675.4 | H4: =Table5[[#This Row],[Year 4]]*(1+'01_Assumptions'!$B$15) -> 1214488.9 | I4: =Table5[[#This Row],[Year 5]]*(1+'01_Assumptions'!$B$15) -> 1238778.7 | J4: =Table5[[#This Row],[Year 6]]*(1+'01_Assumptions'!$B$15) -> 1263554.2 | K4: =Table5[[#This Row],[Year 7]]*(1+'01_Assumptions'!$B$15) -> 1288825.3 | L4: =Table5[[#This Row],[Year 8]]*(1+'01_Assumptions'!$B$15) -> 1314601.8 | M4: =Table5[[#This Row],[Year 9]]*(1+'01_Assumptions'!$B$15) -> 1340893.9 | N4: =Table5[[#This Row],[Year 10]]*(1+'01_Assumptions'!$B$15) -> 1367711.7 | O4: =Table5[[#This Row],[Year 11]]*(1+'01_Assumptions'!$B$15) -> 1395066 | P4: =Table5[[#This Row],[Year 12]]*(1+'01_Assumptions'!$B$15) -> 1422967.3 | Q4: =Table5[[#This Row],[Year 13]]*(1+'01_Assumptions'!$B$15) -> 1451426.6 | R4: =Table5[[#This Row],[Year 14]]*(1+'01_Assumptions'!$B$15) -> 1480455.2 | S4: =Table5[[#This Row],[Year 15]]*(1+'01_Assumptions'!$B$15) -> 1510064.3 | T4: =Table5[[#This Row],[Year 16]]*(1+'01_Assumptions'!$B$15) -> 1540265.6 | U4: =Table5[[#This Row],[Year 17]]*(1+'01_Assumptions'!$B$15) -> 1571070.9 | V4: =Table5[[#This Row],[Year 18]]*(1+'01_Assumptions'!$B$15) -> 1602492.3 | W4: =Table5[[#This Row],[Year 19]]*(1+'01_Assumptions'!$B$15) -> 1634542.1 | X4: =Table5[[#This Row],[Year 20]]*(1+'01_Assumptions'!$B$15) -> 1667233 | Y4: =Table5[[#This Row],[Year 21]]*(1+'01_Assumptions'!$B$15) -> 1700577.6 | Z4: =Table5[[#This Row],[Year 22]]*(1+'01_Assumptions'!$B$15) -> 1734589.2 | AA4: =Table5[[#This Row],[Year 23]]*(1+'01_Assumptions'!$B$15) -> 1769281 | AB4: =Table5[[#This Row],[Year 24]]*(1+'01_Assumptions'!$B$15) -> 1804666.6
A5: EBITDA | B5: € | C5: 0 | D5: =D3-D4 -> 5270545.9 | E5: =E3-E4 -> 5343354.8 | F5: =F3-F4 -> 5417134.2 | G5: =G3-G4 -> 5491896.1 | H5: =H3-H4 -> 5567652.9 | I5: =I3-I4 -> 5644417 | J5: =J3-J4 -> 5722201.1 | K5: =K3-K4 -> 5801017.7 | ... AB5: =AB3-AB4 -> 7311912.7
A15: Definitions:
A16: EBITDA: Earnings Before Interests Taxes Depreciation and Amortization. Measures the project's operating profitability .

Sheet 05_Depreciation
A2: Parameter | B2: Unit | C2: Year 0 | D2: Year 1 | E2: Year 2 | F2: Year 3 | G2: Year 4 | H2: Year 5 | I2: Year 6 | J2: Year 7 | K2: Year 8 | L2: Year 9 | M2: Year 10 | N2: Year 11 | O2: Year 12 | P2: Year 13 | Q2: Year 14 | R2: Year 15 | S2: Year 16 | T2: Year 17 | U2: Year 18 | V2: Year 19 | W2: Year 20 | X2: Year 21 | Y2: Year 22 | Z2: Year 23 | AA2: Year 24 | AB2: Year 25
A3: CAPEX | B3: € | C3: ='01_Assumptions'!B11*10^6 -> 85000000 | D3: 0 | E3: 0 | F3: 0 | G3: 0 | H3: 0 | I3: 0 | J3: 0 | K3: 0 | L3: 0 | M3: 0 | N3: 0 | O3: 0 | P3: 0 | Q3: 0 | R3: 0 | S3: 0 | T3: 0 | U3: 0 | V3: 0 | W3: 0 | X3: 0 | Y3: 0 | Z3: 0 | AA3: 0 | AB3: 0
A4: Depreciation period | B4: year | C4: 25
A5: Depreciation method | B5: N/A | C5: straight-line
A6: Depreciation rate | B6: % | C6: N/A | D6: =1/$C$4 -> 0.04 | E6: =1/$C$4 -> 0.04 | F6: =1/$C$4 -> 0.04 | G6: =1/$C$4 -> 0.04 | H6: =1/$C$4 -> 0.04 | I6: =1/$C$4 -> 0.04 | J6: =1/$C$4 -> 0.04 | K6: =1/$C$4 -> 0.04 | ... AB6: =1/$C$4 -> 0.04
A7: Annual depreciation | B7: € | C7: =0 -> 0 | D7: =$C$3*D6 -> 3400000 | E7: =$C$3*E6 -> 3400000 | F7: =$C$3*F6 -> 3400000 | G7: =$C$3*G6 -> 3400000 | H7: =$C$3*H6 -> 3400000 | I7: =$C$3*I6 -> 3400000 | J7: =$C$3*J6 -> 3400000 | K7: =$C$3*K6 -> 3400000 | ... AB7: =$C$3*AB6 -> 3400000
A8: Accumulated depreciation | B8: € | C8: =C7 -> 0 | D8: =D7 -> 3400000 | E8: =Table57[[#This Row],[Year 1]]+E7 -> 6800000 | F8: =Table57[[#This Row],[Year 2]]+F7 -> 10200000 | G8: =Table57[[#This Row],[Year 3]]+G7 -> 13600000 | H8: =Table57[[#This Row],[Year 4]]+H7 -> 17000000 | I8: =Table57[[#This Row],[Year 5]]+I7 -> 20400000 | J8: =Table57[[#This Row],[Year 6]]+J7 -> 23800000 | K8: =Table57[[#This Row],[Year 7]]+K7 -> 27200000 | L8: =Table57[[#This Row],[Year 8]]+L7 -> 30600000 | M8: =Table57[[#This Row],[Year 9]]+M7 -> 34000000 | N8: =Table57[[#This Row],[Year 10]]+N7 -> 37400000 | O8: =Table57[[#This Row],[Year 11]]+O7 -> 40800000 | P8: =Table57[[#This Row],[Year 12]]+P7 -> 44200000 | Q8: =Table57[[#This Row],[Year 13]]+Q7 -> 47600000 | R8: =Table57[[#This Row],[Year 14]]+R7 -> 51000000 | S8: =Table57[[#This Row],[Year 15]]+S7 -> 54400000 | T8: =Table57[[#This Row],[Year 16]]+T7 -> 57800000 | U8: =Table57[[#This Row],[Year 17]]+U7 -> 61200000 | V8: =Table57[[#This Row],[Year 18]]+V7 -> 64600000 | W8: =Table57[[#This Row],[Year 19]]+W7 -> 68000000 | X8: =Table57[[#This Row],[Year 20]]+X7 -> 71400000 | Y8: =Table57[[#This Row],[Year 21]]+Y7 -> 74800000 | Z8: =Table57[[#This Row],[Year 22]]+Z7 -> 78200000 | AA8: =Table57[[#This Row],[Year 23]]+AA7 -> 81600000 | AB8: =Table57[[#This Row],[Year 24]]+AB7 -> 85000000
A9: Book Value | B9: € | C9: =C3-C8 -> 85000000 | D9: =C9-D7 -> 81600000 | E9: =D9-E7 -> 78200000 | F9: =E9-F7 -> 74800000 | G9: =F9-G7 -> 71400000 | H9: =G9-H7 -> 68000000 | I9: =H9-I7 -> 64600000 | J9: =I9-J7 -> 61200000 | K9: =J9-K7 -> 57800000 | ... AB9: =AA9-AB7 -> 0
A18: Definitions:
A19: Depreciation is the accounting allocation of an asset's cost over its useful life.

Sheet 06_Financing
A2: Parameter | B2: Unit | C2: Year 0 | D2: Year 1 | E2: Year 2 | F2: Year 3 | G2: Year 4 | H2: Year 5 | I2: Year 6 | J2: Year 7 | K2: Year 8 | L2: Year 9 | M2: Year 10 | N2: Year 11 | O2: Year 12 | P2: Year 13 | Q2: Year 14 | R2: Year 15 | S2: Year 16 | T2: Year 17 | U2: Year 18 | V2: Year 19 | W2: Year 20 | X2: Year 21 | Y2: Year 22 | Z2: Year 23 | AA2: Year 24 | AB2: Year 25
A3: CAPEX | B3: € | C3: ='01_Assumptions'!B11*10^6 -> 85000000
A4: Opening Debt Balance | B4: € | C4: N/A | D4: =C10 -> 63750000 | E4: =D10 -> 59500000 | F4: =E10 -> 55250000 | G4: =F10 -> 51000000 | H4: =G10 -> 46750000 | I4: =H10 -> 42500000 | J4: =I10 -> 38250000 | K4: =J10 -> 34000000 | ... R4: =Q10 -> 4250000
A5: Initial Equity | B5: € | C5: =C3*'01_Assumptions'!B23 -> 21250000
A6: Interest rate | B6: % | C6: ='01_Assumptions'!B25 -> 0.0225
A7: Debt tenor | B7: year | C7: ='01_Assumptions'!B24 -> 15
A8: Interest expense | B8: € | C8: N/A | D8: =$D$4*$C$6 -> 1434375 | E8: =$E$4*$C$6 -> 1338750 | F8: =$F$4*$C$6 -> 1243125 | G8: =$G$4*$C$6 -> 1147500 | H8: =$H$4*$C$6 -> 1051875 | I8: =$I$4*$C$6 -> 956250 | J8: =$J$4*$C$6 -> 860625 | K8: =$K$4*$C$6 -> 765000 | L8: =$L$4*$C$6 -> 669375 | M8: =$M$4*$C$6 -> 573750 | N8: =$N$4*$C$6 -> 478125 | O8: =$O$4*$C$6 -> 382500 | P8: =$P$4*$C$6 -> 286875 | Q8: =$Q$4*$C$6 -> 191250 | R8: =$R$4*$C$6 -> 95625
A9: Principal repayment | B9: € | C9: 0 | D9: =$C$10/$C$7 -> 4250000 | E9: =$C$10/$C$7 -> 4250000 | F9: =$C$10/$C$7 -> 4250000 | G9: =$C$10/$C$7 -> 4250000 | H9: =$C$10/$C$7 -> 4250000 | I9: =$C$10/$C$7 -> 4250000 | J9: =$C$10/$C$7 -> 4250000 | K9: =$C$10/$C$7 -> 4250000 | ... R9: =$C$10/$C$7 -> 4250000
A10: Closing Debt Balance | B10: € | C10: =C3*'01_Assumptions'!B22 -> 63750000 | D10: =D4-D9 -> 59500000 | E10: =E4-E9 -> 55250000 | F10: =F4-F9 -> 51000000 | G10: =G4-G9 -> 46750000 | H10: =H4-H9 -> 42500000 | I10: =I4-I9 -> 38250000 | J10: =J4-J9 -> 34000000 | K10: =K4-K9 -> 29750000 | ... R10: =R4-R9 -> 0
A11: Debt service | B11: € | C11: N/A | D11: =D9+D8 -> 5684375 | E11: =E9+E8 -> 5588750 | F11: =F9+F8 -> 5493125 | G11: =G9+G8 -> 5397500 | H11: =H9+H8 -> 5301875 | I11: =I9+I8 -> 5206250 | J11: =J9+J8 -> 5110625 | K11: =K9+K8 -> 5015000 | ... R11: =R9+R8 -> 4345625

Sheet 07_Cash_Flow
A2: Parameter | B2: Unit | C2: Year 0 | D2: Year 1 | E2: Year 2 | F2: Year 3 | G2: Year 4 | H2: Year 5 | I2: Year 6 | J2: Year 7 | K2: Year 8 | L2: Year 9 | M2: Year 10 | N2: Year 11 | O2: Year 12 | P2: Year 13 | Q2: Year 14 | R2: Year 15 | S2: Year 16 | T2: Year 17 | U2: Year 18 | V2: Year 19 | W2: Year 20 | X2: Year 21 | Y2: Year 22 | Z2: Year 23 | AA2: Year 24 | AB2: Year 25
A3: Annual Revenue | B3: € | C3: ='03_Revenues'!C5 -> 0 | D3: ='03_Revenues'!D5 -> 6392545.9 | E3: ='03_Revenues'!E5 -> 6487794.8 | F3: ='03_Revenues'!F5 -> 6584463 | G3: ='03_Revenues'!G5 -> 6682571.5 | H3: ='03_Revenues'!H5 -> 6782141.8 | I3: ='03_Revenues'!I5 -> 6883195.7 | J3: ='03_Revenues'!J5 -> 6985755.3 | ... AB3: ='03_Revenues'!AB5 -> 9116579.3
A4: OPEX | B4: € | C4: =Table5[[#This Row],[Year 0]] -> 0 | D4: =Table5[[#This Row],[Year 1]] -> 1122000 | E4: =Table5[[#This Row],[Year 2]] -> 1144440 | F4: =Table5[[#This Row],[Year 3]] -> 1167328.8 | G4: =Table5[[#This Row],[Year 4]] -> 1190675.4 | H4: =Table5[[#This Row],[Year 5]] -> 1214488.9 | I4: =Table5[[#This Row],[Year 6]] -> 1238778.7 | J4: =Table5[[#This Row],[Year 7]] -> 1263554.2 | K4: =Table5[[#This Row],[Year 8]] -> 1288825.3 | L4: =Table5[[#This Row],[Year 9]] -> 1314601.8 | M4: =Table5[[#This Row],[Year 10]] -> 1340893.9 | N4: =Table5[[#This Row],[Year 11]] -> 1367711.7 | O4: =Table5[[#This Row],[Year 12]] -> 1395066 | P4: =Table5[[#This Row],[Year 13]] -> 1422967.3 | Q4: =Table5[[#This Row],[Year 14]] -> 1451426.6 | R4: =Table5[[#This Row],[Year 15]] -> 1480455.2 | S4: =Table5[[#This Row],[Year 16]] -> 1510064.3 | T4: =Table5[[#This Row],[Year 17]] -> 1540265.6 | U4: =Table5[[#This Row],[Year 18]] -> 1571070.9 | V4: =Table5[[#This Row],[Year 19]] -> 1602492.3 | W4: =Table5[[#This Row],[Year 20]] -> 1634542.1 | X4: =Table5[[#This Row],[Year 21]] -> 1667233 | Y4: =Table5[[#This Row],[Year 22]] -> 1700577.6 | Z4: =Table5[[#This Row],[Year 23]] -> 1734589.2 | AA4: =Table5[[#This Row],[Year 24]] -> 1769281 | AB4: =Table5[[#This Row],[Year 25]] -> 1804666.6
A5: EBITDA | B5: € | C5: =C3-C4 -> 0 | D5: =D3-D4 -> 5270545.9 | E5: =E3-E4 -> 5343354.8 | F5: =F3-F4 -> 5417134.2 | G5: =G3-G4 -> 5491896.1 | H5: =H3-H4 -> 5567652.9 | I5: =I3-I4 -> 5644417 | J5: =J3-J4 -> 5722201.1 | ... AB5: =AB3-AB4 -> 7311912.7
A6: Depreciation | B6: € | C6: ='05_Depreciation'!C7 -> 0 | D6: ='05_Depreciation'!D7 -> 3400000 | E6: ='05_Depreciation'!E7 -> 3400000 | F6: ='05_Depreciation'!F7 -> 3400000 | G6: ='05_Depreciation'!G7 -> 3400000 | H6: ='05_Depreciation'!H7 -> 3400000 | I6: ='05_Depreciation'!I7 -> 3400000 | J6: ='05_Depreciation'!J7 -> 3400000 | ... AB6: ='05_Depreciation'!AB7 -> 3400000
A7: EBIT | B7: € | C7: =C5-C6 -> 0 | D7: =D5-D6 -> 1870545.9 | E7: =E5-E6 -> 1943354.8 | F7: =F5-F6 -> 2017134.2 | G7: =G5-G6 -> 2091896.1 | H7: =H5-H6 -> 2167652.9 | I7: =I5-I6 -> 2244417 | J7: =J5-J6 -> 2322201.1 | ... AB7: =AB5-AB6 -> 3911912.7
A8: Corporate Tax | B8: € | C8: =C7*'01_Assumptions'!$B$21 -> 0 | D8: =D7*'01_Assumptions'!$B$21 -> 467636.47 | E8: =E7*'01_Assumptions'!$B$21 -> 485838.7 | F8: =F7*'01_Assumptions'!$B$21 -> 504283.54 | G8: =G7*'01_Assumptions'!$B$21 -> 522974.02 | H8: =H7*'01_Assumptions'!$B$21 -> 541913.22 | I8: =I7*'01_Assumptions'!$B$21 -> 561104.25 | J8: =J7*'01_Assumptions'!$B$21 -> 580550.26 | ... AB8: =AB7*'01_Assumptions'!$B$21 -> 977978.17
A9: NOPAT | B9: € | C9: =C7-C8 -> 0 | D9: =D7-D8 -> 1402909.4 | E9: =E7-E8 -> 1457516.1 | F9: =F7-F8 -> 1512850.6 | G9: =G7-G8 -> 1568922.1 | H9: =H7-H8 -> 1625739.7 | I9: =I7-I8 -> 1683312.8 | J9: =J7-J8 -> 1741650.8 | ... AB9: =AB7-AB8 -> 2933934.5
A10: Depreciation | B10: € | C10: =C6 -> 0 | D10: =D6 -> 3400000 | E10: =E6 -> 3400000 | F10: =F6 -> 3400000 | G10: =G6 -> 3400000 | H10: =H6 -> 3400000 | I10: =I6 -> 3400000 | J10: =J6 -> 3400000 | ... AB10: =AB6 -> 3400000
A11: CAPEX | B11: € | C11: 85000000 | D11: 0 | E11: 0 | F11: 0 | G11: 0 | H11: 0 | I11: 0 | J11: 0 | K11: 0 | L11: 0 | M11: 0 | N11: 0 | O11: 0 | P11: 0 | Q11: 0 | R11: 0 | S11: 0 | T11: 0 | U11: 0 | V11: 0 | W11: 0 | X11: 0 | Y11: 0 | Z11: 0 | AA11: 0 | AB11: 0
A12: Unlevered Free Cash Flow | B12: € | C12: =C9+C10-C11 -> -85000000 | D12: =D9+D10-D11 -> 4802909.4 | E12: =E9+E10-E11 -> 4857516.1 | F12: =F9+F10-F11 -> 4912850.6 | G12: =G9+G10-G11 -> 4968922.1 | H12: =H9+H10-H11 -> 5025739.7 | I12: =I9+I10-I11 -> 5083312.8 | J12: =J9+J10-J11 -> 5141650.8 | ... AB12: =AB9+AB10-AB11 -> 6333934.5
A17: Definitions:
A18: EBIT: measures operating profit after depreciation and amortization but before interest and taxes.
A19: EBT: is profit before taxes after deducting interest expenses from EBIT.
A20: Net Income: is the profit remaining after operating costs, depreciation, interest and taxes.
A21: Non-cash expense: reduces accounting profit without creating a cash outflow in the current period.
A22: Cash Flow: measures the actual cash generated or consumed by the project during a given period.
A23: Net Operating Profit After Tax: is the project's operating profit after tax, before financing effects.
A24: Unlevered Free Cash Flow: is the cash generated by a project before considering debt financing and equity distributions.
A25: Equity Cash Flow: is the cash available to equity investors after operating costs, taxes, capital expenditures and debt payments.
A29: Cash flow to equity = cash available to equity investors after debt payments.

Sheet 08_DCF_Analysis
A2: Parameter | B2: Unit | C2: Year 0 | D2: Year 1 | E2: Year 2 | F2: Year 3 | G2: Year 4 | H2: Year 5 | I2: Year 6 | J2: Year 7 | K2: Year 8 | L2: Year 9 | M2: Year 10 | N2: Year 11 | O2: Year 12 | P2: Year 13 | Q2: Year 14 | R2: Year 15 | S2: Year 16 | T2: Year 17 | U2: Year 18 | V2: Year 19 | W2: Year 20 | X2: Year 21 | Y2: Year 22 | Z2: Year 23 | AA2: Year 24 | AB2: Year 25
A3: Unlevered Free Cash Flow (UFCF) | B3: € | C3: ='07_Cash_Flow'!C12 -> -85000000 | D3: ='07_Cash_Flow'!D12 -> 4802909.4 | E3: ='07_Cash_Flow'!E12 -> 4857516.1 | F3: ='07_Cash_Flow'!F12 -> 4912850.6 | G3: ='07_Cash_Flow'!G12 -> 4968922.1 | H3: ='07_Cash_Flow'!H12 -> 5025739.7 | I3: ='07_Cash_Flow'!I12 -> 5083312.8 | J3: ='07_Cash_Flow'!J12 -> 5141650.8 | ... AB3: ='07_Cash_Flow'!AB12 -> 6333934.5
A4: Cumulative UFCF | B4: € | C4: =C3 -> -85000000 | D4: =Table10[[#This Row],[Year 0]]+D3 -> -80197091 | E4: =Table10[[#This Row],[Year 1]]+E3 -> -75339574 | F4: =Table10[[#This Row],[Year 2]]+F3 -> -70426724 | G4: =Table10[[#This Row],[Year 3]]+G3 -> -65457802 | H4: =Table10[[#This Row],[Year 4]]+H3 -> -60432062 | I4: =Table10[[#This Row],[Year 5]]+I3 -> -55348749 | J4: =Table10[[#This Row],[Year 6]]+J3 -> -50207099 | K4: =Table10[[#This Row],[Year 7]]+K3 -> -45006335 | L4: =Table10[[#This Row],[Year 8]]+L3 -> -39745675 | M4: =Table10[[#This Row],[Year 9]]+M3 -> -34424325 | N4: =Table10[[#This Row],[Year 10]]+N3 -> -29041480 | O4: =Table10[[#This Row],[Year 11]]+O3 -> -23596328 | P4: =Table10[[#This Row],[Year 12]]+P3 -> -18088044 | Q4: =Table10[[#This Row],[Year 13]]+Q3 -> -12515794 | R4: =Table10[[#This Row],[Year 14]]+R3 -> -6878734.6 | S4: =Table10[[#This Row],[Year 15]]+S3 -> -1176010.6 | T4: =Table10[[#This Row],[Year 16]]+T3 -> 4593243 | U4: =Table10[[#This Row],[Year 17]]+U3 -> 10429902 | V4: =Table10[[#This Row],[Year 18]]+V3 -> 16334853 | W4: =Table10[[#This Row],[Year 19]]+W3 -> 22308993 | X4: =Table10[[#This Row],[Year 20]]+X3 -> 28353230 | Y4: =Table10[[#This Row],[Year 21]]+Y3 -> 34468485 | Z4: =Table10[[#This Row],[Year 22]]+Z3 -> 40655687 | AA4: =Table10[[#This Row],[Year 23]]+AA3 -> 46915779 | AB4: =Table10[[#This Row],[Year 24]]+AB3 -> 53249713
A5: Discount Rate / WACC | B5: % | C5: 0 | D5: ='01_Assumptions'!$B$28 -> 0.03265625 | E5: ='01_Assumptions'!$B$28 -> 0.03265625 | F5: ='01_Assumptions'!$B$28 -> 0.03265625 | G5: ='01_Assumptions'!$B$28 -> 0.03265625 | H5: ='01_Assumptions'!$B$28 -> 0.03265625 | I5: ='01_Assumptions'!$B$28 -> 0.03265625 | J5: ='01_Assumptions'!$B$28 -> 0.03265625 | K5: ='01_Assumptions'!$B$28 -> 0.03265625 | ... AB5: ='01_Assumptions'!$B$28 -> 0.03265625
A6: Discount Factor | B6: - | C6: =1/(1+C5) -> 1 | D6: =Table10[[#This Row],[Year 0]]/(1+D5) -> 0.96837646 | E6: =Table10[[#This Row],[Year 1]]/(1+E5) -> 0.93775296 | F6: =Table10[[#This Row],[Year 2]]/(1+F5) -> 0.90809789 | G6: =Table10[[#This Row],[Year 3]]/(1+G5) -> 0.87938062 | H6: =Table10[[#This Row],[Year 4]]/(1+H5) -> 0.85157148 | I6: =Table10[[#This Row],[Year 5]]/(1+I5) -> 0.82464178 | J6: =Table10[[#This Row],[Year 6]]/(1+J5) -> 0.79856368 | K6: =Table10[[#This Row],[Year 7]]/(1+K5) -> 0.77331027 | L6: =Table10[[#This Row],[Year 8]]/(1+L5) -> 0.74885546 | M6: =Table10[[#This Row],[Year 9]]/(1+M5) -> 0.72517399 | N6: =Table10[[#This Row],[Year 10]]/(1+N5) -> 0.70224142 | O6: =Table10[[#This Row],[Year 11]]/(1+O5) -> 0.68003406 | P6: =Table10[[#This Row],[Year 12]]/(1+P5) -> 0.65852897 | Q6: =Table10[[#This Row],[Year 13]]/(1+Q5) -> 0.63770395 | R6: =Table10[[#This Row],[Year 14]]/(1+R5) -> 0.61753749 | S6: =Table10[[#This Row],[Year 15]]/(1+S5) -> 0.59800877 | T6: =Table10[[#This Row],[Year 16]]/(1+T5) -> 0.57909761 | U6: =Table10[[#This Row],[Year 17]]/(1+U5) -> 0.5607845 | V6: =Table10[[#This Row],[Year 18]]/(1+V5) -> 0.5430505 | W6: =Table10[[#This Row],[Year 19]]/(1+W5) -> 0.52587732 | X6: =Table10[[#This Row],[Year 20]]/(1+X5) -> 0.50924722 | Y6: =Table10[[#This Row],[Year 21]]/(1+Y5) -> 0.49314302 | Z6: =Table10[[#This Row],[Year 22]]/(1+Z5) -> 0.47754809 | AA6: =Table10[[#This Row],[Year 23]]/(1+AA5) -> 0.46244632 | AB6: =Table10[[#This Row],[Year 24]]/(1+AB5) -> 0.44782213
A7: Discounted Cash Flow (Present Value of UFCF) | B7: € | C7: =C3*C6 -> -85000000 | D7: =D3*D6 -> 4651024.4 | E7: =E3*E6 -> 4555150.1 | F7: =F3*F6 -> 4461349.3 | G7: =G3*G6 -> 4369573.7 | H7: =H3*H6 -> 4279776.6 | I7: =I3*I6 -> 4191912.1 | J7: =J3*J6 -> 4105935.6 | ... AB7: =AB3*AB6 -> 2836476.1
A8: Cumulative Present Value | B8: € | C8: =C7 -> -85000000 | D8: =Table10[[#This Row],[Year 0]]+D7 -> -80348976 | E8: =Table10[[#This Row],[Year 1]]+E7 -> -75793825 | F8: =Table10[[#This Row],[Year 2]]+F7 -> -71332476 | G8: =Table10[[#This Row],[Year 3]]+G7 -> -66962902 | H8: =Table10[[#This Row],[Year 4]]+H7 -> -62683126 | I8: =Table10[[#This Row],[Year 5]]+I7 -> -58491214 | J8: =Table10[[#This Row],[Year 6]]+J7 -> -54385278 | K8: =Table10[[#This Row],[Year 7]]+K7 -> -50363475 | L8: =Table10[[#This Row],[Year 8]]+L7 -> -46424001 | M8: =Table10[[#This Row],[Year 9]]+M7 -> -42565096 | N8: =Table10[[#This Row],[Year 10]]+N7 -> -38785039 | O8: =Table10[[#This Row],[Year 11]]+O7 -> -35082150 | P8: =Table10[[#This Row],[Year 12]]+P7 -> -31454785 | Q8: =Table10[[#This Row],[Year 13]]+Q7 -> -27901340 | R8: =Table10[[#This Row],[Year 14]]+R7 -> -24420244 | S8: =Table10[[#This Row],[Year 15]]+S7 -> -21009965 | T8: =Table10[[#This Row],[Year 16]]+T7 -> -17669004 | U8: =Table10[[#This Row],[Year 17]]+U7 -> -14395896 | V8: =Table10[[#This Row],[Year 18]]+V7 -> -11189210 | W8: =Table10[[#This Row],[Year 19]]+W7 -> -8047545.2 | X8: =Table10[[#This Row],[Year 20]]+X7 -> -4969534 | Y8: =Table10[[#This Row],[Year 21]]+Y7 -> -1953838.9 | Z8: =Table10[[#This Row],[Year 22]]+Z7 -> 1000847.6 | AA8: =Table10[[#This Row],[Year 23]]+AA7 -> 3895804 | AB8: =Table10[[#This Row],[Year 24]]+AB7 -> 6732280
A12: Definitions:
A13: Discount Rate: The rate used to convert future cash flows into their present value.
A14: WACC: The weighted average cost of debt and equity used as the discount rate for unlevered cash flows.
A15: Discount Factor: A factor used to convert a future cash flow into its present value.
A16: Present Value (PV): The value today of a future cash flow after applying the discount rate.
A17: Discounted Cash Flow (DCF): A valuation method that estimates the value of an investment by discounting its future cash flows to the present.
A18: NPV: The present value of all future cash flows minus the initial investment.
A19: IRR: The discount rate at which the NPV of an investment equals zero.

Sheet 09_Investment_Returns
A2: Parameter | B2: Unit | C2: Result
A3: Initial Investment | B3: € | C3: ='01_Assumptions'!B11*10^6 -> 85000000
A4: Discount Rate | B4: % | C4: ='01_Assumptions'!B28 -> 0.03265625
A5: NPV | B5: € | C5: ='08_DCF_Analysis'!AB8 -> 6732280
A6: IRR | B6: % | C6: =IRR('08_DCF_Analysis'!C3:AB3) -> 0.03936708
A7: ROI | B7: % | C7: =SUM('07_Cash_Flow'!D9:AB9)/'09_Investment_Returns'!C3 -> 0.62646721
A8: Simple Payback Period | B8: years | C8: 17
A9: Discounted Paybakc Period | B9: years | C9: 23
A10: Profitability index | B10: N/A | C10: =SUM('08_DCF_Analysis'!D7:AB7)/'05_Depreciation'!C3 -> 1.0792033
A17: Definitions:
A18: Profitability Index: measures how much present value is generated per €1 of initial investment.
A19: Unlevered: means that the impact of debt financing is excluded.
A20: IRR: is the discount rate at which the NPV of an investment equals zero.
A21: ROI: measures the return generated by an investment relative to the initial investment.
A22: Payback Period: is the time required for a project to recover its initial investment from its cash flows.
A23: Simple Payback Period: measures the time needed to recover the initial investment using undiscounted cash flows.
A24: Discounted Payback Period: measures the time needed to recover the initial investment using discounted cash flows.

Sheet 07_Equity_Cash_Flow
A2: Parameter | B2: Unit | C2: Year 0 | D2: Year 1 | E2: Year 2 | F2: Year 3 | G2: Year 4 | H2: Year 5 | I2: Year 6 | J2: Year 7 | K2: Year 8 | L2: Year 9 | M2: Year 10 | N2: Year 11 | O2: Year 12 | P2: Year 13 | Q2: Year 14 | R2: Year 15 | S2: Year 16 | T2: Year 17 | U2: Year 18 | V2: Year 19 | W2: Year 20 | X2: Year 21 | Y2: Year 22 | Z2: Year 23 | AA2: Year 24 | AB2: Year 25
A3: Annual Revenue | B3: € | C3: ='03_Revenues'!C5 -> 0 | D3: ='03_Revenues'!D5 -> 6392545.9 | E3: ='03_Revenues'!E5 -> 6487794.8 | F3: ='03_Revenues'!F5 -> 6584463 | G3: ='03_Revenues'!G5 -> 6682571.5 | H3: ='03_Revenues'!H5 -> 6782141.8 | I3: ='03_Revenues'!I5 -> 6883195.7 | J3: ='03_Revenues'!J5 -> 6985755.3 | ... AB3: ='03_Revenues'!AB5 -> 9116579.3
A4: OPEX | B4: € | C4: =Table5[[#This Row],[Year 0]] -> 0 | D4: =Table5[[#This Row],[Year 1]] -> 1122000 | E4: =Table5[[#This Row],[Year 2]] -> 1144440 | F4: =Table5[[#This Row],[Year 3]] -> 1167328.8 | G4: =Table5[[#This Row],[Year 4]] -> 1190675.4 | H4: =Table5[[#This Row],[Year 5]] -> 1214488.9 | I4: =Table5[[#This Row],[Year 6]] -> 1238778.7 | J4: =Table5[[#This Row],[Year 7]] -> 1263554.2 | K4: =Table5[[#This Row],[Year 8]] -> 1288825.3 | L4: =Table5[[#This Row],[Year 9]] -> 1314601.8 | M4: =Table5[[#This Row],[Year 10]] -> 1340893.9 | N4: =Table5[[#This Row],[Year 11]] -> 1367711.7 | O4: =Table5[[#This Row],[Year 12]] -> 1395066 | P4: =Table5[[#This Row],[Year 13]] -> 1422967.3 | Q4: =Table5[[#This Row],[Year 14]] -> 1451426.6 | R4: =Table5[[#This Row],[Year 15]] -> 1480455.2 | S4: =Table5[[#This Row],[Year 16]] -> 1510064.3 | T4: =Table5[[#This Row],[Year 17]] -> 1540265.6 | U4: =Table5[[#This Row],[Year 18]] -> 1571070.9 | V4: =Table5[[#This Row],[Year 19]] -> 1602492.3 | W4: =Table5[[#This Row],[Year 20]] -> 1634542.1 | X4: =Table5[[#This Row],[Year 21]] -> 1667233 | Y4: =Table5[[#This Row],[Year 22]] -> 1700577.6 | Z4: =Table5[[#This Row],[Year 23]] -> 1734589.2 | AA4: =Table5[[#This Row],[Year 24]] -> 1769281 | AB4: =Table5[[#This Row],[Year 25]] -> 1804666.6
A5: EBITDA | B5: € | C5: =C3-C4 -> 0 | D5: =D3-D4 -> 5270545.9 | E5: =E3-E4 -> 5343354.8 | F5: =F3-F4 -> 5417134.2 | G5: =G3-G4 -> 5491896.1 | H5: =H3-H4 -> 5567652.9 | I5: =I3-I4 -> 5644417 | J5: =J3-J4 -> 5722201.1 | ... AB5: =AB3-AB4 -> 7311912.7
A6: Depreciation | B6: € | C6: ='05_Depreciation'!C7 -> 0 | D6: ='05_Depreciation'!D7 -> 3400000 | E6: ='05_Depreciation'!E7 -> 3400000 | F6: ='05_Depreciation'!F7 -> 3400000 | G6: ='05_Depreciation'!G7 -> 3400000 | H6: ='05_Depreciation'!H7 -> 3400000 | I6: ='05_Depreciation'!I7 -> 3400000 | J6: ='05_Depreciation'!J7 -> 3400000 | ... AB6: ='05_Depreciation'!AB7 -> 3400000
A7: EBIT | B7: € | C7: =C5-C6 -> 0 | D7: =D5-D6 -> 1870545.9 | E7: =E5-E6 -> 1943354.8 | F7: =F5-F6 -> 2017134.2 | G7: =G5-G6 -> 2091896.1 | H7: =H5-H6 -> 2167652.9 | I7: =I5-I6 -> 2244417 | J7: =J5-J6 -> 2322201.1 | ... AB7: =AB5-AB6 -> 3911912.7
A8: Interest Expense | B8: € | C8: =Table578[[#This Row],[Year 0]] -> N/A | D8: =Table578[[#This Row],[Year 1]] -> 1434375 | E8: =Table578[[#This Row],[Year 2]] -> 1338750 | F8: =Table578[[#This Row],[Year 3]] -> 1243125 | G8: =Table578[[#This Row],[Year 4]] -> 1147500 | H8: =Table578[[#This Row],[Year 5]] -> 1051875 | I8: =Table578[[#This Row],[Year 6]] -> 956250 | J8: =Table578[[#This Row],[Year 7]] -> 860625 | K8: =Table578[[#This Row],[Year 8]] -> 765000 | L8: =Table578[[#This Row],[Year 9]] -> 669375 | M8: =Table578[[#This Row],[Year 10]] -> 573750 | N8: =Table578[[#This Row],[Year 11]] -> 478125 | O8: =Table578[[#This Row],[Year 12]] -> 382500 | P8: =Table578[[#This Row],[Year 13]] -> 286875 | Q8: =Table578[[#This Row],[Year 14]] -> 191250 | R8: =Table578[[#This Row],[Year 15]] -> 95625 | S8: =Table578[[#This Row],[Year 16]] -> 0 | T8: =Table578[[#This Row],[Year 17]] -> 0 | U8: =Table578[[#This Row],[Year 18]] -> 0 | V8: =Table578[[#This Row],[Year 19]] -> 0 | W8: =Table578[[#This Row],[Year 20]] -> 0 | X8: =Table578[[#This Row],[Year 21]] -> 0 | Y8: =Table578[[#This Row],[Year 22]] -> 0 | Z8: =Table578[[#This Row],[Year 23]] -> 0 | AA8: =Table578[[#This Row],[Year 24]] -> 0 | AB8: =Table578[[#This Row],[Year 25]] -> 0
A9: EBT | B9: € | C9: 0 | D9: =D7-D8 -> 436170.88 | E9: =E7-E8 -> 604604.81 | F9: =F7-F8 -> 774009.15 | G9: =G7-G8 -> 944396.08 | H9: =H7-H8 -> 1115777.9 | I9: =I7-I8 -> 1288167 | J9: =J7-J8 -> 1461576.1 | K9: =K7-K8 -> 1636017.7 | ... AB9: =AB7-AB8 -> 3911912.7
A10: Corporate Tax | B10: € | C10: =C9*'01_Assumptions'!$B$21 -> 0 | D10: =D9*'01_Assumptions'!$B$21 -> 109042.72 | E10: =E9*'01_Assumptions'!$B$21 -> 151151.2 | F10: =F9*'01_Assumptions'!$B$21 -> 193502.29 | G10: =G9*'01_Assumptions'!$B$21 -> 236099.02 | H10: =H9*'01_Assumptions'!$B$21 -> 278944.47 | I10: =I9*'01_Assumptions'!$B$21 -> 322041.75 | J10: =J9*'01_Assumptions'!$B$21 -> 365394.01 | ... AB10: =AB9*'01_Assumptions'!$B$21 -> 977978.17
A11: Net Income | B11: € | C11: =C9-C10 -> 0 | D11: =D9-D10 -> 327128.16 | E11: =E9-E10 -> 453453.61 | F11: =F9-F10 -> 580506.86 | G11: =G9-G10 -> 708297.06 | H11: =H9-H10 -> 836833.41 | I11: =I9-I10 -> 966125.26 | J11: =J9-J10 -> 1096182 | ... AB11: =AB9-AB10 -> 2933934.5
A12: Depreciation | B12: € | C12: =C6 -> 0 | D12: =D6 -> 3400000 | E12: =E6 -> 3400000 | F12: =F6 -> 3400000 | G12: =G6 -> 3400000 | H12: =H6 -> 3400000 | I12: =I6 -> 3400000 | J12: =J6 -> 3400000 | ... AB12: =AB6 -> 3400000
A13: CAPEX | B13: € | C13: 85000000 | D13: 0 | E13: 0 | F13: 0 | G13: 0 | H13: 0 | I13: 0 | J13: 0 | K13: 0 | L13: 0 | M13: 0 | N13: 0 | O13: 0 | P13: 0 | Q13: 0 | R13: 0 | S13: 0 | T13: 0 | U13: 0 | V13: 0 | W13: 0 | X13: 0 | Y13: 0 | Z13: 0 | AA13: 0 | AB13: 0
A14: Principal Repayment | B14: € | C14: ='06_Financing'!C9 -> 0 | D14: ='06_Financing'!D9 -> 4250000 | E14: ='06_Financing'!E9 -> 4250000 | F14: ='06_Financing'!F9 -> 4250000 | G14: ='06_Financing'!G9 -> 4250000 | H14: ='06_Financing'!H9 -> 4250000 | I14: ='06_Financing'!I9 -> 4250000 | J14: ='06_Financing'!J9 -> 4250000 | ... AB14: ='06_Financing'!AB9 -> 0
A15: Net Cash Flow | B15: € | C15: =C11+C12-C13-C14 -> -85000000 | D15: =D11+D12-D13-D14 -> -522871.84 | E15: =E11+E12-E13-E14 -> -396546.39 | F15: =F11+F12-F13-F14 -> -269493.14 | G15: =G11+G12-G13-G14 -> -141702.94 | H15: =H11+H12-H13-H14 -> -13166.588 | I15: =I11+I12-I13-I14 -> 116125.26 | J15: =J11+J12-J13-J14 -> 246182.04 | ... AB15: =AB11+AB12-AB13-AB14 -> 6333934.5
A20: Definitions:
A21: EBIT: measures operating profit after depreciation and amortization but before interest and taxes.
A22: EBT: is profit before taxes after deducting interest expenses from EBIT.
A23: Net Income: is the profit remaining after operating costs, depreciation, interest and taxes.
A24: Non-cash expense: reduces accounting profit without creating a cash outflow in the current period.
A25: Cash Flow: measures the actual cash generated or consumed by the project during a given period.
A26: CAPEX: is the cash investment required to acquire or build long-term assets.
A27: Project / Unlevered Cash Flow: measures the cash generated by the project independently of its financing structure
A28: Equity Cash Flow: measures the cash available to equity investors after debt-related cash flows.
A32: Cash flow to equity = cash available to equity investors after debt payments.
